taskbox/__init__.py
taskbox/api.py
taskbox/auth.py
taskbox/db.py
taskbox/manage.py
taskbox/run.py
taskbox/schema.sql
taskbox/token.py
taskbox/static/site.css
taskbox/templates/base.html
taskbox/templates/run.html
taskbox/templates/auth/login.html
taskbox/templates/auth/register.html
taskbox/templates/auth/update.html
taskbox/templates/manage/create_device.html
taskbox/templates/manage/create_task.html
taskbox/templates/manage/manage.html
taskbox/templates/manage/update_device.html
taskbox/templates/manage/update_task.html
taskbox/templates/token/create.html
tests/__init__.py
tests/preload.sql
tests/test_api.py
tests/test_auth.py
tests/test_init.py
tests/test_manage.py
tests/test_run.py
tests/test_token.py
taskbox-0.1.0.dist-info/LICENSE
taskbox-0.1.0.dist-info/METADATA
taskbox-0.1.0.dist-info/WHEEL
taskbox-0.1.0.dist-info/top_level.txt
taskbox-0.1.0.dist-info/RECORD
