Metadata-Version: 2.1
Name: taskbox
Version: 0.1.0
Summary: A minimal task manager for automated test.
Home-page: https://github.com/mcpcpc/taskbox
Author: Michael Czigler
Author-email: contact@mcpcpc.com
License: BSD-3-Clause
Project-URL: Donate, https://www.paypal.me/mcpcpc/usd5
Project-URL: Source Code, https://github.com/mcpcpc/taskbox/
Project-URL: Issue Tracker, https://github.com/mcpcpc/taskbox/issues
Keywords: flask,automation,test,framework,wsgi
Classifier: Development Status :: 5 - Production/Stable
Classifier: Framework :: Flask
Classifier: License :: OSI Approved :: BSD License
Classifier: Operating System :: OS Independent
Classifier: Programming Language :: Python
Classifier: Topic :: Internet :: WWW/HTTP :: WSGI :: Application
Requires-Python: >=3.7
License-File: LICENSE
Requires-Dist: Flask (>=2.2)
Requires-Dist: PyJWT (>=2.6)
Provides-Extra: test
Requires-Dist: coverage ; extra == 'test'
